arcan/__init__.py
arcan/agent/__init__.py
arcan/agent/chains.py
arcan/agent/llm.py
arcan/agent/scrapping.py
arcan/agent/streaming_gpt.py
arcan/agent/templates.py
arcan/agent/vectorstores.py
arcan/engines/__init__.py
arcan/engines/io.py
arcan/governance/__init__.py
arcan/governance/catalog/__init__.py
arcan/governance/lifecycle/__init__.py
arcan/governance/mdm/__init__.py
arcan/governance/quality/__init__.py
arcan/ml/__init__.py
arcan/orchestrator/__init__.py
arcan/processing/__init__.py
arcan/processing/pipelines/__init__.py
arcan/processing/quality/__init__.py
arcan/processing/transformations/__init__.py
arcan/session/__init__.py
arcan/session/auth.py
arcan/storage/__init__.py
main.py
arcan-1.5.0.dist-info/LICENSE
arcan-1.5.0.dist-info/METADATA
arcan-1.5.0.dist-info/WHEEL
arcan-1.5.0.dist-info/entry_points.txt
arcan-1.5.0.dist-info/RECORD
