Metadata-Version: 2.1
Name: arcan
Version: 1.5.0
Summary: A multiheaded modern data bridging package based on pipeline manifests to integrate between any modern (and old) data stack tools
License: arcan.ai Non-Commercial Open Source License
Author: Carlos D. Escobar-Valbuena
Author-email: carlosdavidescobar@gmail.com
Requires-Python: >=3.10,<4.0
Classifier: License :: Other/Proprietary License
Classifier: Programming Language :: Python :: 3
Classifier: Programming Language :: Python :: 3.10
Classifier: Programming Language :: Python :: 3.11
Requires-Dist: beautifulsoup4 (>=4.12.2,<5.0.0)
Requires-Dist: black (>=23.3.0,<24.0.0)
Requires-Dist: faiss-cpu (>=1.7.4,<2.0.0)
Requires-Dist: fastapi (>=0.98,<0.100)
Requires-Dist: ffmpeg (>=1.4,<2.0)
Requires-Dist: fschat (>=0.2.23,<0.3.0)
Requires-Dist: httpx (>=0.24.1,<0.25.0)
Requires-Dist: langchain (>=0.0.254,<0.0.255)
Requires-Dist: lxml (>=4.9.3,<5.0.0)
Requires-Dist: modal-client (>=0.49.2509,<0.51.0)
Requires-Dist: openai (>=0.27.8,<0.28.0)
Requires-Dist: tiktoken (>=0.4.0,<0.5.0)
Requires-Dist: torch (>=2.0.1,<3.0.0)
Requires-Dist: transformers (>=4.31.0,<5.0.0)
Requires-Dist: urllib3 (<=2.0)
Requires-Dist: uvicorn (>=0.22.0,<0.23.0)
Requires-Dist: whisper (>=1.1.10,<2.0.0)
